{
	"Content": [{
			"title": "平台",
			"child": [{
					"title": "aistudio",
					"href": "https://aistudio.baidu.com/aistudio/competition"
				},
				{
					"title": "biendata",
					"href": "https://www.biendata.com/competition/"
				}
			]
		},
		{
			"title": "比赛",
			"child": [
				{
					"title": "CCKS 2020: 面向中文短文本的实体链指任务",
					"href": "https://www.biendata.com/competition/ccks_2020_el/"
				},
				{
					"title": "实体链指任务baseline",
					"href": "https://github.com/PaddlePaddle/Research/tree/master/KG/DuEL_Baseline"
				},
				{
					"title": "实体链接：一份“由浅入深”的综述",
					"href": "https://zhuanlan.zhihu.com/p/100248426"
				},
				{
					"title": "CCKS&百度 2019中文短文本的实体链指 第一名解决方案",
					"href": "https://github.com/panchunguang/ccks_baidu_entity_link"
				},
				{
					"title": "多因子融合的实体识别与链指消歧",
					"href": "https://cloud.tencent.com/developer/article/1491361"
				},
				{
					"title": "2020语言与智能技术竞赛：事件抽取任务",
					"href": "https://aistudio.baidu.com/aistudio/competition/detail/32"
				},
				{
					"title": "事件抽取任务baseline",
					"href": "https://github.com/PaddlePaddle/Research/tree/master/KG/DuEE_baseline"
				},
				{
					"title": "百度aistudio事件抽取比赛总结——记一次使用MRC方式做事件抽取任务的尝试",
					"href": "https://zhuanlan.zhihu.com/p/141237763"
				}
			]
		}
	],
	"Info": {
		"title": "NLP相关比赛",
		"group": "学习"
	}
}
